{
  "metadata": {
    "generated_at": "2025-08-14T11:38:14.955300",
    "description": "Feature statistics for anomaly detection",
    "version": "1.0.0",
    "total_tables": 17,
    "total_features": 52
  },
  "tables": {
    "erpx_dev_rm_procurement.grn_items": {
      "database_name": "erpx_dev_rm_procurement",
      "table_name": "grn_items",
      "full_table_name": "erpx_dev_rm_procurement.grn_items",
      "row_count": 14513,
      "column_count": 38,
      "strategies": [
        "univariate",
        "multivariate"
      ],
      "last_updated": "2025-08-14T11:38:16.809924",
      "features": {
        "quantity": {
          "count": 14513,
          "mean": 2822.194,
          "std": 2540.3889,
          "median": 2136.0,
          "min": 4.0,
          "max": 31870.0,
          "q1": 1149.0,
          "q3": 3668.0,
          "iqr": 2519.0,
          "mad": 1139.0,
          "skewness": 2.4502,
          "kurtosis": 10.4194,
          "thresholds": {
            "iqr_method": {
              "lower_bound": 0,
              "upper_bound": 7446.5
            },
            "z_score_method": {
              "lower_bound": -4798.9727,
              "upper_bound": 10443.3608
            },
            "mad_method": {
              "lower_bound": -1850.5,
              "upper_bound": 6122.5
            }
          }
        },
        "count": {
          "count": 14513,
          "mean": 60.1426,
          "std": 48.7887,
          "median": 54.0,
          "min": 5.0,
          "max": 4850.0,
          "q1": 40.0,
          "q3": 72.0,
          "iqr": 32.0,
          "mad": 16.0,
          "skewness": 65.6097,
          "kurtosis": 6402.2632,
          "thresholds": {
            "iqr_method": {
              "lower_bound": 0,
              "upper_bound": 120.0
            },
            "z_score_method": {
              "lower_bound": -86.2234,
              "upper_bound": 206.5086
            },
            "mad_method": {
              "lower_bound": -2.0,
              "upper_bound": 110.0
            }
          }
        },
        "received_boxes": {
          "count": 13731,
          "mean": 94.7705,
          "std": 96.9664,
          "median": 73.0,
          "min": 0.0,
          "max": 6069.0,
          "q1": 40.0,
          "q3": 124.0,
          "iqr": 84.0,
          "mad": 39.0,
          "skewness": 18.8242,
          "kurtosis": 1062.1253,
          "thresholds": {
            "iqr_method": {
              "lower_bound": 0,
              "upper_bound": 250.0
            },
            "z_score_method": {
              "lower_bound": -196.1286,
              "upper_bound": 385.6697
            },
            "mad_method": {
              "lower_bound": -63.5,
              "upper_bound": 209.5
            }
          }
        },
        "soft_percentage": {
          "count": 12040,
          "mean": 0.0264,
          "std": 1.3359,
          "median": 0.0,
          "min": 0.0,
          "max": 132.0,
          "q1": 0.0,
          "q3": 0.0,
          "iqr": 0.0,
          "mad": 0.0,
          "skewness": 84.6039,
          "kurtosis": 8027.448,
          "thresholds": {
            "iqr_method": {
              "lower_bound": 0,
              "upper_bound": 0.0
            },
            "z_score_method": {
              "lower_bound": -3.9813,
              "upper_bound": 4.0342
            },
            "mad_method": {
              "lower_bound": 0.0,
              "upper_bound": 0.0
            }
          }
        },
        "boxes": {
          "count": 14513,
          "mean": 93.1495,
          "std": 80.2021,
          "median": 72.0,
          "min": 1.0,
          "max": 867.0,
          "q1": 39.0,
          "q3": 122.0,
          "iqr": 83.0,
          "mad": 38.0,
          "skewness": 2.1935,
          "kurtosis": 7.8565,
          "thresholds": {
            "iqr_method": {
              "lower_bound": 0,
              "upper_bound": 246.5
            },
            "z_score_method": {
              "lower_bound": -147.4569,
              "upper_bound": 333.7558
            },
            "mad_method": {
              "lower_bound": -61.0,
              "upper_bound": 205.0
            }
          }
        },
        "antibiotic_test": {
          "count": 14513,
          "mean": 0.0001,
          "std": 0.0083,
          "median": 0.0,
          "min": 0.0,
          "max": 1.0,
          "q1": 0.0,
          "q3": 0.0,
          "iqr": 0.0,
          "mad": 0.0,
          "skewness": 120.4575,
          "kurtosis": 14508.0001,
          "thresholds": {
            "iqr_method": {
              "lower_bound": 0,
              "upper_bound": 0.0
            },
            "z_score_method": {
              "lower_bound": -0.0248,
              "upper_bound": 0.025
            },
            "mad_method": {
              "lower_bound": 0.0,
              "upper_bound": 0.0
            }
          }
        },
        "fungus_percentage": {
          "count": 12040,
          "mean": 0.0111,
          "std": 0.7633,
          "median": 0.0,
          "min": 0.0,
          "max": 71.0,
          "q1": 0.0,
          "q3": 0.0,
          "iqr": 0.0,
          "mad": 0.0,
          "skewness": 82.7321,
          "kurtosis": 7127.5946,
          "thresholds": {
            "iqr_method": {
              "lower_bound": 0,
              "upper_bound": 0.0
            },
            "z_score_method": {
              "lower_bound": -2.2788,
              "upper_bound": 2.3011
            },
            "mad_method": {
              "lower_bound": 0.0,
              "upper_bound": 0.0
            }
          }
        }
      }
    },
    "erpx_dev_rm_procurement.indent_items": {
      "database_name": "erpx_dev_rm_procurement",
      "table_name": "indent_items",
      "full_table_name": "erpx_dev_rm_procurement.indent_items",
      "row_count": 14588,
      "column_count": 20,
      "strategies": [
        "univariate",
        "multivariate"
      ],
      "last_updated": "2025-08-14T11:38:17.690633",
      "features": {
        "expected_count": {
          "count": 14588,
          "mean": 57.2672,
          "std": 30.7099,
          "median": 55.0,
          "min": 1.0,
          "max": 1800.0,
          "q1": 35.0,
          "q3": 75.0,
          "iqr": 40.0,
          "mad": 20.0,
          "skewness": 13.1908,
          "kurtosis": 710.7738,
          "thresholds": {
            "iqr_method": {
              "lower_bound": 0,
              "upper_bound": 135.0
            },
            "z_score_method": {
              "lower_bound": -34.8625,
              "upper_bound": 149.3969
            },
            "mad_method": {
              "lower_bound": -15.0,
              "upper_bound": 125.0
            }
          }
        },
        "expected_qty": {
          "count": 14588,
          "mean": 2838.594,
          "std": 2559.1479,
          "median": 2000.0,
          "min": 10.0,
          "max": 36000.0,
          "q1": 1100.0,
          "q3": 3700.0,
          "iqr": 2600.0,
          "mad": 1000.0,
          "skewness": 2.6915,
          "kurtosis": 14.3612,
          "thresholds": {
            "iqr_method": {
              "lower_bound": 0,
              "upper_bound": 7600.0
            },
            "z_score_method": {
              "lower_bound": -4838.8495,
              "upper_bound": 10516.0376
            },
            "mad_method": {
              "lower_bound": -1500.0,
              "upper_bound": 5500.0
            }
          }
        },
        "expected_price": {
          "count": 14588,
          "mean": 316.4604,
          "std": 112.5181,
          "median": 300.0,
          "min": 0.0,
          "max": 8000.0,
          "q1": 265.0,
          "q3": 350.0,
          "iqr": 85.0,
          "mad": 45.0,
          "skewness": 25.8667,
          "kurtosis": 1573.3192,
          "thresholds": {
            "iqr_method": {
              "lower_bound": 137.5,
              "upper_bound": 477.5
            },
            "z_score_method": {
              "lower_bound": -21.0938,
              "upper_bound": 654.0147
            },
            "mad_method": {
              "lower_bound": 142.5,
              "upper_bound": 457.5
            }
          }
        }
      }
    },
    "erpx_dev_production.pp_inward": {
      "database_name": "erpx_dev_production",
      "table_name": "pp_inward",
      "full_table_name": "erpx_dev_production.pp_inward",
      "row_count": 3269,
      "column_count": 27,
      "strategies": [
        "univariate",
        "multivariate"
      ],
      "last_updated": "2025-08-14T11:38:18.262564",
      "features": {
        "weight_from_gate": {
          "count": 3269,
          "mean": 3660.712,
          "std": 3440.8481,
          "median": 2593.2,
          "min": 2.8,
          "max": 36036.0,
          "q1": 1450.0,
          "q3": 4800.0,
          "iqr": 3350.0,
          "mad": 1459.8,
          "skewness": 2.4228,
          "kurtosis": 9.0125,
          "thresholds": {
            "iqr_method": {
              "lower_bound": 0,
              "upper_bound": 9825.0
            },
            "z_score_method": {
              "lower_bound": -6661.8322,
              "upper_bound": 13983.2562
            },
            "mad_method": {
              "lower_bound": -2516.1,
              "upper_bound": 7702.5
            }
          }
        },
        "count_at_farm_gate": {
          "count": 3269,
          "mean": 53.3191,
          "std": 24.9846,
          "median": 50.0,
          "min": 5.0,
          "max": 200.0,
          "q1": 36.0,
          "q3": 70.0,
          "iqr": 34.0,
          "mad": 15.0,
          "skewness": 1.0119,
          "kurtosis": 1.8713,
          "thresholds": {
            "iqr_method": {
              "lower_bound": 0,
              "upper_bound": 121.0
            },
            "z_score_method": {
              "lower_bound": -21.6347,
              "upper_bound": 128.2728
            },
            "mad_method": {
              "lower_bound": -2.5,
              "upper_bound": 102.5
            }
          }
        },
        "trays_received_from_farm": {
          "count": 3269,
          "mean": 138.8559,
          "std": 162.2466,
          "median": 91.0,
          "min": 1.0,
          "max": 2601.0,
          "q1": 50.0,
          "q3": 168.0,
          "iqr": 118.0,
          "mad": 51.0,
          "skewness": 4.564,
          "kurtosis": 40.0938,
          "thresholds": {
            "iqr_method": {
              "lower_bound": 0,
              "upper_bound": 345.0
            },
            "z_score_method": {
              "lower_bound": -347.884,
              "upper_bound": 625.5959
            },
            "mad_method": {
              "lower_bound": -87.5,
              "upper_bound": 269.5
            }
          }
        },
        "verified_weight": {
          "count": 3245,
          "mean": 3678.6767,
          "std": 4970.755,
          "median": 2546.7,
          "min": 12.567,
          "max": 171306.0,
          "q1": 1393.0,
          "q3": 4696.0329,
          "iqr": 3303.0329,
          "mad": 1447.7,
          "skewness": 16.8593,
          "kurtosis": 502.1279,
          "thresholds": {
            "iqr_method": {
              "lower_bound": 0,
              "upper_bound": 9650.5822
            },
            "z_score_method": {
              "lower_bound": -11233.5882,
              "upper_bound": 18590.9416
            },
            "mad_method": {
              "lower_bound": -2520.25,
              "upper_bound": 7613.65
            }
          }
        },
        "verified_net_weight": {
          "count": 3245,
          "mean": 2726.7991,
          "std": 35748.5017,
          "median": 2477.9925,
          "min": -1994739.0,
          "max": 171184.0,
          "q1": 1345.8,
          "q3": 4479.6875,
          "iqr": 3133.8875,
          "mad": 1401.4925,
          "skewness": -53.8044,
          "kurtosis": 3003.0895,
          "thresholds": {
            "iqr_method": {
              "lower_bound": 0,
              "upper_bound": 9180.5187
            },
            "z_score_method": {
              "lower_bound": -104518.706,
              "upper_bound": 109972.3042
            },
            "mad_method": {
              "lower_bound": -2427.2312,
              "upper_bound": 7383.2162
            }
          }
        },
        "verified_count": {
          "count": 3245,
          "mean": 53.568,
          "std": 24.9905,
          "median": 50.0,
          "min": 1.0,
          "max": 200.0,
          "q1": 36.0,
          "q3": 70.0,
          "iqr": 34.0,
          "mad": 15.0,
          "skewness": 1.0031,
          "kurtosis": 1.8558,
          "thresholds": {
            "iqr_method": {
              "lower_bound": 0,
              "upper_bound": 121.0
            },
            "z_score_method": {
              "lower_bound": -21.4036,
              "upper_bound": 128.5395
            },
            "mad_method": {
              "lower_bound": -2.5,
              "upper_bound": 102.5
            }
          }
        },
        "verified_no_of_trays": {
          "count": 3245,
          "mean": 137.3174,
          "std": 158.252,
          "median": 90.0,
          "min": 1.0,
          "max": 2601.0,
          "q1": 49.0,
          "q3": 167.0,
          "iqr": 118.0,
          "mad": 51.0,
          "skewness": 4.003,
          "kurtosis": 30.131,
          "thresholds": {
            "iqr_method": {
              "lower_bound": 0,
              "upper_bound": 344.0
            },
            "z_score_method": {
              "lower_bound": -337.4386,
              "upper_bound": 612.0735
            },
            "mad_method": {
              "lower_bound": -88.5,
              "upper_bound": 268.5
            }
          }
        },
        "sample_count": {
          "count": 3269,
          "mean": 62.1523,
          "std": 248.9517,
          "median": 0.0,
          "min": 0.0,
          "max": 1847.0,
          "q1": 0.0,
          "q3": 10.0,
          "iqr": 10.0,
          "mad": 0.0,
          "skewness": 4.5257,
          "kurtosis": 20.1093,
          "thresholds": {
            "iqr_method": {
              "lower_bound": 0,
              "upper_bound": 25.0
            },
            "z_score_method": {
              "lower_bound": -684.7028,
              "upper_bound": 809.0075
            },
            "mad_method": {
              "lower_bound": 0.0,
              "upper_bound": 0.0
            }
          }
        }
      }
    },
    "erpx_dev_production.pp_inward_reading": {
      "database_name": "erpx_dev_production",
      "table_name": "pp_inward_reading",
      "full_table_name": "erpx_dev_production.pp_inward_reading",
      "row_count": 7971,
      "column_count": 14,
      "strategies": [
        "univariate",
        "multivariate"
      ],
      "last_updated": "2025-08-14T11:38:18.751780",
      "features": {
        "weight": {
          "count": 7971,
          "mean": 1113.7456,
          "std": 24087.8116,
          "median": 74.0,
          "min": -1994739.0,
          "max": 171184.0,
          "q1": 70.14,
          "q3": 1980.968,
          "iqr": 1910.828,
          "mad": 22.16,
          "skewness": -74.2163,
          "kurtosis": 5991.928,
          "thresholds": {
            "iqr_method": {
              "lower_bound": 0,
              "upper_bound": 4847.21
            },
            "z_score_method": {
              "lower_bound": -71149.6891,
              "upper_bound": 73377.1803
            },
            "mad_method": {
              "lower_bound": -3.56,
              "upper_bound": 151.56
            }
          }
        },
        "total_weight": {
          "count": 7971,
          "mean": 2185.5741,
          "std": 24114.5907,
          "median": 1749.9927,
          "min": -1994739.0,
          "max": 171184.0,
          "q1": 760.41,
          "q3": 3323.1499,
          "iqr": 2562.7399,
          "mad": 1193.5075,
          "skewness": -74.1012,
          "kurtosis": 5978.507,
          "thresholds": {
            "iqr_method": {
              "lower_bound": 0,
              "upper_bound": 7167.2598
            },
            "z_score_method": {
              "lower_bound": -70158.1978,
              "upper_bound": 74529.3461
            },
            "mad_method": {
              "lower_bound": -2427.2837,
              "upper_bound": 5927.2691
            }
          }
        },
        "crates": {
          "count": 7971,
          "mean": 59.0493,
          "std": 131.0765,
          "median": 3.0,
          "min": 1.0,
          "max": 4587.0,
          "q1": 3.0,
          "q3": 70.0,
          "iqr": 67.0,
          "mad": 1.0,
          "skewness": 9.1464,
          "kurtosis": 212.529,
          "thresholds": {
            "iqr_method": {
              "lower_bound": 0,
              "upper_bound": 170.5
            },
            "z_score_method": {
              "lower_bound": -334.1802,
              "upper_bound": 452.2788
            },
            "mad_method": {
              "lower_bound": -0.5,
              "upper_bound": 6.5
            }
          }
        }
      }
    },
    "erpx_dev_production.pp_grading": {
      "database_name": "erpx_dev_production",
      "table_name": "pp_grading",
      "full_table_name": "erpx_dev_production.pp_grading",
      "row_count": 3177,
      "column_count": 12,
      "strategies": [
        "univariate"
      ],
      "last_updated": "2025-08-14T11:38:19.114220",
      "features": {
        "crate_weight": {
          "count": 3177,
          "mean": 1.9891,
          "std": 1.1883,
          "median": 2.2,
          "min": 0.0,
          "max": 22.0,
          "q1": 2.0,
          "q3": 3.0,
          "iqr": 1.0,
          "mad": 0.8,
          "skewness": 0.7181,
          "kurtosis": 24.2741,
          "thresholds": {
            "iqr_method": {
              "lower_bound": 0.5,
              "upper_bound": 4.5
            },
            "z_score_method": {
              "lower_bound": -1.5758,
              "upper_bound": 5.5539
            },
            "mad_method": {
              "lower_bound": -0.6,
              "upper_bound": 5.0
            }
          }
        }
      }
    },
    "erpx_dev_production.pp_grading_grades": {
      "database_name": "erpx_dev_production",
      "table_name": "pp_grading_grades",
      "full_table_name": "erpx_dev_production.pp_grading_grades",
      "row_count": 14702,
      "column_count": 6,
      "strategies": [
        "univariate",
        "multivariate"
      ],
      "last_updated": "2025-08-14T11:38:19.537931",
      "features": {
        "count": {
          "count": 14702,
          "mean": 43.4364,
          "std": 25.7862,
          "median": 37.0,
          "min": 7.0,
          "max": 238.0,
          "q1": 26.0,
          "q3": 55.0,
          "iqr": 29.0,
          "mad": 13.0,
          "skewness": 1.6684,
          "kurtosis": 4.0446,
          "thresholds": {
            "iqr_method": {
              "lower_bound": 0,
              "upper_bound": 98.5
            },
            "z_score_method": {
              "lower_bound": -33.9224,
              "upper_bound": 120.7951
            },
            "mad_method": {
              "lower_bound": -8.5,
              "upper_bound": 82.5
            }
          }
        },
        "uniformity_ratio": {
          "count": 14702,
          "mean": 1.2922,
          "std": 0.2849,
          "median": 1.28,
          "min": 1.0,
          "max": 24.0,
          "q1": 1.2,
          "q3": 1.3,
          "iqr": 0.1,
          "mad": 0.04,
          "skewness": 43.014,
          "kurtosis": 3021.2083,
          "thresholds": {
            "iqr_method": {
              "lower_bound": 1.05,
              "upper_bound": 1.45
            },
            "z_score_method": {
              "lower_bound": 0.4374,
              "upper_bound": 2.147
            },
            "mad_method": {
              "lower_bound": 1.14,
              "upper_bound": 1.42
            }
          }
        }
      }
    },
    "erpx_dev_production.pp_grading_readings": {
      "database_name": "erpx_dev_production",
      "table_name": "pp_grading_readings",
      "full_table_name": "erpx_dev_production.pp_grading_readings",
      "row_count": 135148,
      "column_count": 16,
      "strategies": [
        "univariate",
        "multivariate"
      ],
      "last_updated": "2025-08-14T11:38:24.196301",
      "features": {
        "count": {
          "count": 134473,
          "mean": 36.6088,
          "std": 18.4082,
          "median": 33.0,
          "min": -1.0,
          "max": 238.0,
          "q1": 24.0,
          "q3": 44.0,
          "iqr": 20.0,
          "mad": 10.0,
          "skewness": 1.9524,
          "kurtosis": 7.8927,
          "thresholds": {
            "iqr_method": {
              "lower_bound": 0,
              "upper_bound": 74.0
            },
            "z_score_method": {
              "lower_bound": -18.6159,
              "upper_bound": 91.8336
            },
            "mad_method": {
              "lower_bound": -2.0,
              "upper_bound": 68.0
            }
          }
        },
        "weight": {
          "count": 135148,
          "mean": 59.7294,
          "std": 330.4057,
          "median": 36.06,
          "min": 0.0,
          "max": 18423.0,
          "q1": 36.0,
          "q3": 37.4,
          "iqr": 1.4,
          "mad": 1.14,
          "skewness": 25.0037,
          "kurtosis": 806.2116,
          "thresholds": {
            "iqr_method": {
              "lower_bound": 33.9,
              "upper_bound": 39.5
            },
            "z_score_method": {
              "lower_bound": -931.4877,
              "upper_bound": 1050.9465
            },
            "mad_method": {
              "lower_bound": 32.07,
              "upper_bound": 40.05
            }
          }
        },
        "crates": {
          "count": 135148,
          "mean": 2.4629,
          "std": 16.6316,
          "median": 1.0,
          "min": 0.0,
          "max": 985.0,
          "q1": 1.0,
          "q3": 2.0,
          "iqr": 1.0,
          "mad": 0.0,
          "skewness": 28.0382,
          "kurtosis": 983.9886,
          "thresholds": {
            "iqr_method": {
              "lower_bound": 0,
              "upper_bound": 3.5
            },
            "z_score_method": {
              "lower_bound": -47.4319,
              "upper_bound": 52.3577
            },
            "mad_method": {
              "lower_bound": 1.0,
              "upper_bound": 1.0
            }
          }
        }
      }
    },
    "erpx_dev_production.pp_soaking_lot": {
      "database_name": "erpx_dev_production",
      "table_name": "pp_soaking_lot",
      "full_table_name": "erpx_dev_production.pp_soaking_lot",
      "row_count": 41293,
      "column_count": 7,
      "strategies": [
        "univariate"
      ],
      "last_updated": "2025-08-14T11:38:25.230735",
      "features": {
        "count": {
          "count": 41293,
          "mean": 50.1537,
          "std": 40.242,
          "median": 36.0,
          "min": -1.0,
          "max": 906.0,
          "q1": 26.0,
          "q3": 52.0,
          "iqr": 26.0,
          "mad": 13.0,
          "skewness": 1.8971,
          "kurtosis": 6.4866,
          "thresholds": {
            "iqr_method": {
              "lower_bound": 0,
              "upper_bound": 91.0
            },
            "z_score_method": {
              "lower_bound": -70.5723,
              "upper_bound": 170.8798
            },
            "mad_method": {
              "lower_bound": -9.5,
              "upper_bound": 81.5
            }
          }
        }
      }
    },
    "erpx_dev_production.pp_soaking": {
      "database_name": "erpx_dev_production",
      "table_name": "pp_soaking",
      "full_table_name": "erpx_dev_production.pp_soaking",
      "row_count": 41895,
      "column_count": 19,
      "strategies": [
        "univariate",
        "multivariate"
      ],
      "last_updated": "2025-08-14T11:38:27.360955",
      "features": {
        "soak_time": {
          "count": 41895,
          "mean": 118.2656,
          "std": 45.5783,
          "median": 120.0,
          "min": 1.0,
          "max": 1280.0,
          "q1": 120.0,
          "q3": 120.0,
          "iqr": 0.0,
          "mad": 0.0,
          "skewness": 0.8428,
          "kurtosis": 10.6519,
          "thresholds": {
            "iqr_method": {
              "lower_bound": 120.0,
              "upper_bound": 120.0
            },
            "z_score_method": {
              "lower_bound": -18.4694,
              "upper_bound": 255.0006
            },
            "mad_method": {
              "lower_bound": 120.0,
              "upper_bound": 120.0
            }
          }
        },
        "crate_weight": {
          "count": 41895,
          "mean": 1.3472,
          "std": 1.048,
          "median": 2.0,
          "min": 0.0,
          "max": 27.0,
          "q1": 0.0,
          "q3": 2.2,
          "iqr": 2.2,
          "mad": 0.2,
          "skewness": -0.1532,
          "kurtosis": 6.8156,
          "thresholds": {
            "iqr_method": {
              "lower_bound": 0,
              "upper_bound": 5.5
            },
            "z_score_method": {
              "lower_bound": -1.7967,
              "upper_bound": 4.4911
            },
            "mad_method": {
              "lower_bound": 1.3,
              "upper_bound": 2.7
            }
          }
        },
        "soakin_count": {
          "count": 12428,
          "mean": 38.0853,
          "std": 24.9599,
          "median": 32.0,
          "min": 3.0,
          "max": 1172.0,
          "q1": 22.0,
          "q3": 46.0,
          "iqr": 24.0,
          "mad": 12.0,
          "skewness": 9.5364,
          "kurtosis": 354.802,
          "thresholds": {
            "iqr_method": {
              "lower_bound": 0,
              "upper_bound": 82.0
            },
            "z_score_method": {
              "lower_bound": -36.7945,
              "upper_bound": 112.9651
            },
            "mad_method": {
              "lower_bound": -10.0,
              "upper_bound": 74.0
            }
          }
        }
      }
    },
    "erpx_dev_production.pp_soaking_readings": {
      "database_name": "erpx_dev_production",
      "table_name": "pp_soaking_readings",
      "full_table_name": "erpx_dev_production.pp_soaking_readings",
      "row_count": 35917,
      "column_count": 16,
      "strategies": [
        "univariate",
        "multivariate"
      ],
      "last_updated": "2025-08-14T11:38:28.709962",
      "features": {
        "weight": {
          "count": 35917,
          "mean": 149.4116,
          "std": 26.4126,
          "median": 160.6,
          "min": 0.2,
          "max": 226.72,
          "q1": 150.0,
          "q3": 161.62,
          "iqr": 11.62,
          "mad": 1.4,
          "skewness": -3.0201,
          "kurtosis": 9.6395,
          "thresholds": {
            "iqr_method": {
              "lower_bound": 132.57,
              "upper_bound": 179.05
            },
            "z_score_method": {
              "lower_bound": 70.1738,
              "upper_bound": 228.6494
            },
            "mad_method": {
              "lower_bound": 155.7,
              "upper_bound": 165.5
            }
          }
        },
        "crates": {
          "count": 35917,
          "mean": 3.4895,
          "std": 2.2578,
          "median": 5.0,
          "min": 0.0,
          "max": 8.0,
          "q1": 0.0,
          "q3": 5.0,
          "iqr": 5.0,
          "mad": 0.0,
          "skewness": -0.7603,
          "kurtosis": -1.2209,
          "thresholds": {
            "iqr_method": {
              "lower_bound": 0,
              "upper_bound": 12.5
            },
            "z_score_method": {
              "lower_bound": -3.2839,
              "upper_bound": 10.263
            },
            "mad_method": {
              "lower_bound": 5.0,
              "upper_bound": 5.0
            }
          }
        }
      }
    },
    "erpx_dev_production.pp_soaking_temperature": {
      "database_name": "erpx_dev_production",
      "table_name": "pp_soaking_temperature",
      "full_table_name": "erpx_dev_production.pp_soaking_temperature",
      "row_count": 84969,
      "column_count": 12,
      "strategies": [
        "univariate"
      ],
      "last_updated": "2025-08-14T11:38:31.514314",
      "features": {
        "temperature": {
          "count": 84969,
          "mean": 4.3459,
          "std": 2.2967,
          "median": 4.0225,
          "min": -96.2638,
          "max": 59.5748,
          "q1": 2.859,
          "q3": 5.5568,
          "iqr": 2.6977,
          "mad": 1.3178,
          "skewness": 0.2766,
          "kurtosis": 73.5,
          "thresholds": {
            "iqr_method": {
              "lower_bound": 0,
              "upper_bound": 9.6034
            },
            "z_score_method": {
              "lower_bound": -2.5443,
              "upper_bound": 11.2361
            },
            "mad_method": {
              "lower_bound": -0.59,
              "upper_bound": 8.6349
            }
          }
        }
      }
    },
    "erpx_dev_production.pp_cooking_lot": {
      "database_name": "erpx_dev_production",
      "table_name": "pp_cooking_lot",
      "full_table_name": "erpx_dev_production.pp_cooking_lot",
      "row_count": 1876,
      "column_count": 6,
      "strategies": [
        "univariate"
      ],
      "last_updated": "2025-08-14T11:38:31.778359",
      "features": {
        "count": {
          "count": 1876,
          "mean": 40.274,
          "std": 25.5555,
          "median": 30.0,
          "min": 8.0,
          "max": 132.0,
          "q1": 23.0,
          "q3": 44.0,
          "iqr": 21.0,
          "mad": 13.0,
          "skewness": 1.8117,
          "kurtosis": 3.0274,
          "thresholds": {
            "iqr_method": {
              "lower_bound": 0,
              "upper_bound": 75.5
            },
            "z_score_method": {
              "lower_bound": -36.3924,
              "upper_bound": 116.9404
            },
            "mad_method": {
              "lower_bound": -15.5,
              "upper_bound": 75.5
            }
          }
        }
      }
    },
    "erpx_dev_production.pp_cooking": {
      "database_name": "erpx_dev_production",
      "table_name": "pp_cooking",
      "full_table_name": "erpx_dev_production.pp_cooking",
      "row_count": 1871,
      "column_count": 14,
      "strategies": [
        "univariate",
        "multivariate"
      ],
      "last_updated": "2025-08-14T11:38:32.038563",
      "features": {
        "cooking_temp": {
          "count": 1871,
          "mean": 49.262,
          "std": 33.4828,
          "median": 72.0,
          "min": 0.0,
          "max": 76.0,
          "q1": 0.0,
          "q3": 72.0,
          "iqr": 72.0,
          "mad": 0.0,
          "skewness": -0.7921,
          "kurtosis": -1.3725,
          "thresholds": {
            "iqr_method": {
              "lower_bound": 0,
              "upper_bound": 180.0
            },
            "z_score_method": {
              "lower_bound": -51.1864,
              "upper_bound": 149.7104
            },
            "mad_method": {
              "lower_bound": 72.0,
              "upper_bound": 72.0
            }
          }
        },
        "chilling_temp": {
          "count": 1871,
          "mean": 6.1603,
          "std": 4.1894,
          "median": 9.0,
          "min": 0.0,
          "max": 15.0,
          "q1": 0.0,
          "q3": 9.0,
          "iqr": 9.0,
          "mad": 0.0,
          "skewness": -0.7871,
          "kurtosis": -1.3665,
          "thresholds": {
            "iqr_method": {
              "lower_bound": 0,
              "upper_bound": 22.5
            },
            "z_score_method": {
              "lower_bound": -6.4077,
              "upper_bound": 18.7284
            },
            "mad_method": {
              "lower_bound": 9.0,
              "upper_bound": 9.0
            }
          }
        }
      }
    },
    "erpx_dev_production.pp_cooking_readings": {
      "database_name": "erpx_dev_production",
      "table_name": "pp_cooking_readings",
      "full_table_name": "erpx_dev_production.pp_cooking_readings",
      "row_count": 139355,
      "column_count": 14,
      "strategies": [
        "multivariate"
      ],
      "last_updated": "2025-08-14T11:38:36.425159",
      "features": {
        "temperature": {
          "count": 139355,
          "mean": 14.0728,
          "std": 17.3935,
          "median": 6.0,
          "min": 0.0,
          "max": 85.0276,
          "q1": 4.0,
          "q3": 18.125,
          "iqr": 14.125,
          "mad": 4.0,
          "skewness": 2.5819,
          "kurtosis": 6.2423,
          "thresholds": {
            "iqr_method": {
              "lower_bound": 0,
              "upper_bound": 39.3125
            },
            "z_score_method": {
              "lower_bound": -38.1077,
              "upper_bound": 66.2533
            },
            "mad_method": {
              "lower_bound": -8.0,
              "upper_bound": 20.0
            }
          }
        },
        "temperature_type": {
          "count": 139355,
          "mean": 2.9598,
          "std": 1.091,
          "median": 3.0,
          "min": 1.0,
          "max": 4.0,
          "q1": 2.0,
          "q3": 4.0,
          "iqr": 2.0,
          "mad": 1.0,
          "skewness": -0.3181,
          "kurtosis": -1.4846,
          "thresholds": {
            "iqr_method": {
              "lower_bound": 0,
              "upper_bound": 7.0
            },
            "z_score_method": {
              "lower_bound": -0.3131,
              "upper_bound": 6.2328
            },
            "mad_method": {
              "lower_bound": -0.5,
              "upper_bound": 6.5
            }
          }
        },
        "temperature_fault": {
          "count": 139355,
          "mean": 0.5852,
          "std": 0.4987,
          "median": 1.0,
          "min": 0.0,
          "max": 2.0,
          "q1": 0.0,
          "q3": 1.0,
          "iqr": 1.0,
          "mad": 0.0,
          "skewness": -0.2739,
          "kurtosis": -1.7376,
          "thresholds": {
            "iqr_method": {
              "lower_bound": 0,
              "upper_bound": 2.5
            },
            "z_score_method": {
              "lower_bound": -0.9109,
              "upper_bound": 2.0813
            },
            "mad_method": {
              "lower_bound": 1.0,
              "upper_bound": 1.0
            }
          }
        }
      }
    },
    "erpx_dev_production.pp_packing": {
      "database_name": "erpx_dev_production",
      "table_name": "pp_packing",
      "full_table_name": "erpx_dev_production.pp_packing",
      "row_count": 1431,
      "column_count": 26,
      "strategies": [
        "univariate",
        "multivariate"
      ],
      "last_updated": "2025-08-14T11:38:36.769026",
      "features": {
        "net_weight": {
          "count": 1431,
          "mean": 425.0209,
          "std": 12015.6802,
          "median": 0.908,
          "min": 0.03,
          "max": 454017.0,
          "q1": 0.454,
          "q3": 4.605,
          "iqr": 4.151,
          "mad": 0.454,
          "skewness": 37.6342,
          "kurtosis": 1418.1368,
          "thresholds": {
            "iqr_method": {
              "lower_bound": 0,
              "upper_bound": 10.8315
            },
            "z_score_method": {
              "lower_bound": -35622.0196,
              "upper_bound": 36472.0614
            },
            "mad_method": {
              "lower_bound": -0.681,
              "upper_bound": 2.497
            }
          }
        },
        "min_weight": {
          "count": 1431,
          "mean": 1.7773,
          "std": 2.7628,
          "median": 1.03,
          "min": 0.0,
          "max": 13.615,
          "q1": 0.4625,
          "q3": 1.06,
          "iqr": 0.5975,
          "mad": 0.505,
          "skewness": 2.6201,
          "kurtosis": 6.1212,
          "thresholds": {
            "iqr_method": {
              "lower_bound": 0,
              "upper_bound": 1.9563
            },
            "z_score_method": {
              "lower_bound": -6.5112,
              "upper_bound": 10.0657
            },
            "mad_method": {
              "lower_bound": -0.7375,
              "upper_bound": 2.7975
            }
          }
        },
        "no_of_pouches": {
          "count": 1431,
          "mean": 10.3082,
          "std": 7.6365,
          "median": 10.0,
          "min": 0.0,
          "max": 60.0,
          "q1": 5.0,
          "q3": 16.0,
          "iqr": 11.0,
          "mad": 6.0,
          "skewness": 0.5925,
          "kurtosis": 0.9303,
          "thresholds": {
            "iqr_method": {
              "lower_bound": 0,
              "upper_bound": 32.5
            },
            "z_score_method": {
              "lower_bound": -12.6015,
              "upper_bound": 33.2178
            },
            "mad_method": {
              "lower_bound": -11.0,
              "upper_bound": 31.0
            }
          }
        },
        "pouch_weight": {
          "count": 1431,
          "mean": 0.023,
          "std": 0.055,
          "median": 0.01,
          "min": 0.0,
          "max": 1.055,
          "q1": 0.003,
          "q3": 0.019,
          "iqr": 0.016,
          "mad": 0.009,
          "skewness": 8.6316,
          "kurtosis": 114.2046,
          "thresholds": {
            "iqr_method": {
              "lower_bound": 0,
              "upper_bound": 0.043
            },
            "z_score_method": {
              "lower_bound": -0.142,
              "upper_bound": 0.188
            },
            "mad_method": {
              "lower_bound": -0.0215,
              "upper_bound": 0.0415
            }
          }
        },
        "min_glaze": {
          "count": 1027,
          "mean": 10.9446,
          "std": 2.2628,
          "median": 11.0,
          "min": 0.0,
          "max": 50.0,
          "q1": 11.0,
          "q3": 11.0,
          "iqr": 0.0,
          "mad": 0.0,
          "skewness": 5.2989,
          "kurtosis": 99.3053,
          "thresholds": {
            "iqr_method": {
              "lower_bound": 11.0,
              "upper_bound": 11.0
            },
            "z_score_method": {
              "lower_bound": 4.1563,
              "upper_bound": 17.7329
            },
            "mad_method": {
              "lower_bound": 11.0,
              "upper_bound": 11.0
            }
          }
        },
        "max_glaze": {
          "count": 1027,
          "mean": 14.7869,
          "std": 5.3895,
          "median": 15.0,
          "min": 0.0,
          "max": 150.0,
          "q1": 15.0,
          "q3": 15.0,
          "iqr": 0.0,
          "mad": 0.0,
          "skewness": 17.1089,
          "kurtosis": 404.3439,
          "thresholds": {
            "iqr_method": {
              "lower_bound": 15.0,
              "upper_bound": 15.0
            },
            "z_score_method": {
              "lower_bound": -1.3815,
              "upper_bound": 30.9553
            },
            "mad_method": {
              "lower_bound": 15.0,
              "upper_bound": 15.0
            }
          }
        }
      }
    },
    "erpx_dev_production.pp_packing_master_readings": {
      "database_name": "erpx_dev_production",
      "table_name": "pp_packing_master_readings",
      "full_table_name": "erpx_dev_production.pp_packing_master_readings",
      "row_count": 289919,
      "column_count": 13,
      "strategies": [
        "univariate",
        "multivariate"
      ],
      "last_updated": "2025-08-14T11:38:45.734278",
      "features": {
        "weight": {
          "count": 289919,
          "mean": 7.4855,
          "std": 3.8606,
          "median": 5.46,
          "min": -0.112,
          "max": 25.22,
          "q1": 5.32,
          "q3": 10.14,
          "iqr": 4.82,
          "mad": 0.72,
          "skewness": 1.5473,
          "kurtosis": 1.8658,
          "thresholds": {
            "iqr_method": {
              "lower_bound": 0,
              "upper_bound": 17.37
            },
            "z_score_method": {
              "lower_bound": -4.0962,
              "upper_bound": 19.0672
            },
            "mad_method": {
              "lower_bound": 2.94,
              "upper_bound": 7.98
            }
          }
        },
        "weight_limit": {
          "count": 289919,
          "mean": 7.4814,
          "std": 3.8648,
          "median": 5.45,
          "min": 0.27,
          "max": 93.984,
          "q1": 5.317,
          "q3": 10.2,
          "iqr": 4.883,
          "mad": 0.738,
          "skewness": 1.654,
          "kurtosis": 4.4006,
          "thresholds": {
            "iqr_method": {
              "lower_bound": 0,
              "upper_bound": 17.5244
            },
            "z_score_method": {
              "lower_bound": -4.1128,
              "upper_bound": 19.0757
            },
            "mad_method": {
              "lower_bound": 2.867,
              "upper_bound": 8.033
            }
          }
        }
      }
    },
    "erpx_dev_production.pp_packing_glazing_reading": {
      "database_name": "erpx_dev_production",
      "table_name": "pp_packing_glazing_reading",
      "full_table_name": "erpx_dev_production.pp_packing_glazing_reading",
      "row_count": 17127,
      "column_count": 16,
      "strategies": [
        "univariate",
        "multivariate"
      ],
      "last_updated": "2025-08-14T11:38:46.662690",
      "features": {
        "frozen_weight": {
          "count": 17127,
          "mean": 0.6744,
          "std": 0.4892,
          "median": 0.538,
          "min": 0.0,
          "max": 7.179,
          "q1": 0.388,
          "q3": 1.056,
          "iqr": 0.668,
          "mad": 0.512,
          "skewness": 0.7386,
          "kurtosis": 6.2237,
          "thresholds": {
            "iqr_method": {
              "lower_bound": 0,
              "upper_bound": 2.058
            },
            "z_score_method": {
              "lower_bound": -0.7933,
              "upper_bound": 2.142
            },
            "mad_method": {
              "lower_bound": -1.254,
              "upper_bound": 2.33
            }
          }
        },
        "de_glazed_weight": {
          "count": 17127,
          "mean": 0.5881,
          "std": 0.4272,
          "median": 0.466,
          "min": 0.0,
          "max": 6.735,
          "q1": 0.333,
          "q3": 0.92,
          "iqr": 0.587,
          "mad": 0.449,
          "skewness": 0.7591,
          "kurtosis": 7.0267,
          "thresholds": {
            "iqr_method": {
              "lower_bound": 0,
              "upper_bound": 1.8005
            },
            "z_score_method": {
              "lower_bound": -0.6935,
              "upper_bound": 1.8697
            },
            "mad_method": {
              "lower_bound": -1.1055,
              "upper_bound": 2.0375
            }
          }
        },
        "glaze_percentage": {
          "count": 17126,
          "mean": 10.3757,
          "std": 5.9554,
          "median": 12.6623,
          "min": -165.1429,
          "max": 88.5318,
          "q1": 7.9812,
          "q3": 14.0187,
          "iqr": 6.0375,
          "mad": 1.8386,
          "skewness": -1.7914,
          "kurtosis": 49.8332,
          "thresholds": {
            "iqr_method": {
              "lower_bound": 0,
              "upper_bound": 23.0749
            },
            "z_score_method": {
              "lower_bound": -7.4906,
              "upper_bound": 28.242
            },
            "mad_method": {
              "lower_bound": 6.2272,
              "upper_bound": 19.0975
            }
          }
        },
        "duration": {
          "count": 17127,
          "mean": 79.0817,
          "std": 737.7076,
          "median": 44.0,
          "min": 0.0,
          "max": 39041.0,
          "q1": 28.0,
          "q3": 59.0,
          "iqr": 31.0,
          "mad": 15.0,
          "skewness": 33.3939,
          "kurtosis": 1316.1856,
          "thresholds": {
            "iqr_method": {
              "lower_bound": 0,
              "upper_bound": 105.5
            },
            "z_score_method": {
              "lower_bound": -2134.0411,
              "upper_bound": 2292.2046
            },
            "mad_method": {
              "lower_bound": -8.5,
              "upper_bound": 96.5
            }
          }
        }
      }
    }
  }
}
